wordSense/__init__.py
wordSense/senses.py
Wordsense-3.1.dist-info/METADATA
Wordsense-3.1.dist-info/WHEEL
Wordsense-3.1.dist-info/top_level.txt
Wordsense-3.1.dist-info/RECORD
