Metadata-Version: 2.1
Name: Wordsense
Version: 3.1
Summary: Get Meaning of Ambiguous word
Home-page: https://github.com/DASHANANT/Wordsense
Author: Anant Dashpute
Author-email: <anantdashpute@gmail.com>
License: UNKNOWN
Keywords: WSD,Sense,Disambiguation,Lesk,word-sense,stem,Knowlege based,wordnet,NLP
Platform: UNKNOWN
Classifier: Development Status :: 4 - Beta
Classifier: Programming Language :: Python :: 3
Classifier: Programming Language :: Python :: 3.6
Classifier: Programming Language :: Python :: 3.7
Classifier: Programming Language :: Python :: 3.8
Classifier: Programming Language :: Python :: 3.9
Classifier: Operating System :: OS Independent
Classifier: Intended Audience :: Science/Research
Requires-Dist: nltk
